.gitignore
LICENSE
MANIFEST.in
README
README.md
setup.py
admin_bootstrap/__init__.py
admin_bootstrap.egg-info/PKG-INFO
admin_bootstrap.egg-info/SOURCES.txt
admin_bootstrap.egg-info/dependency_links.txt
admin_bootstrap.egg-info/not-zip-safe
admin_bootstrap.egg-info/top_level.txt
admin_bootstrap/static/admin/responsive.css
admin_bootstrap/static/admin/css/admin.css
admin_bootstrap/static/admin/img/glyphicons-halflings-white.png
admin_bootstrap/static/admin/img/glyphicons-halflings.png
admin_bootstrap/static/admin/js/.jshintrc
admin_bootstrap/static/admin/js/README.md
admin_bootstrap/static/admin/js/bootstrap-alert.js
admin_bootstrap/static/admin/js/bootstrap-button.js
admin_bootstrap/static/admin/js/bootstrap-carousel.js
admin_bootstrap/static/admin/js/bootstrap-collapse.js
admin_bootstrap/static/admin/js/bootstrap-dropdown.js
admin_bootstrap/static/admin/js/bootstrap-modal.js
admin_bootstrap/static/admin/js/bootstrap-popover.js
admin_bootstrap/static/admin/js/bootstrap-scrollspy.js
admin_bootstrap/static/admin/js/bootstrap-tab.js
admin_bootstrap/static/admin/js/bootstrap-tooltip.js
admin_bootstrap/static/admin/js/bootstrap-transition.js
admin_bootstrap/static/admin/js/bootstrap-typeahead.js
admin_bootstrap/static/admin/js/tests/index.html
admin_bootstrap/static/admin/js/tests/phantom.js
admin_bootstrap/static/admin/js/tests/server.js
admin_bootstrap/static/admin/js/tests/unit/bootstrap-alert.js
admin_bootstrap/static/admin/js/tests/unit/bootstrap-button.js
admin_bootstrap/static/admin/js/tests/unit/bootstrap-carousel.js
admin_bootstrap/static/admin/js/tests/unit/bootstrap-collapse.js
admin_bootstrap/static/admin/js/tests/unit/bootstrap-dropdown.js
admin_bootstrap/static/admin/js/tests/unit/bootstrap-modal.js
admin_bootstrap/static/admin/js/tests/unit/bootstrap-phantom.js
admin_bootstrap/static/admin/js/tests/unit/bootstrap-popover.js
admin_bootstrap/static/admin/js/tests/unit/bootstrap-scrollspy.js
admin_bootstrap/static/admin/js/tests/unit/bootstrap-tab.js
admin_bootstrap/static/admin/js/tests/unit/bootstrap-tooltip.js
admin_bootstrap/static/admin/js/tests/unit/bootstrap-transition.js
admin_bootstrap/static/admin/js/tests/unit/bootstrap-typeahead.js
