Metadata-Version: 1.0
Name: admin-bootstrap
Version: 0.7.0
Summary: Django admin templates that are compatible with Twitter Bootstrap version 2.1.0
Home-page: https://github.com/dryan/admin_bootstrap
Author: Daniel Ryan
Author-email: dryan@dryan.com
License: BSD 3 Clause License
Platform: UNKNOWN
